collectionbatchtool.py
specifymodels.py
CollectionBatchTool-0.1.6.dist-info/DESCRIPTION.rst
CollectionBatchTool-0.1.6.dist-info/METADATA
CollectionBatchTool-0.1.6.dist-info/RECORD
CollectionBatchTool-0.1.6.dist-info/WHEEL
CollectionBatchTool-0.1.6.dist-info/metadata.json
CollectionBatchTool-0.1.6.dist-info/top_level.txt
