Metadata-Version: 2.0
Name: CollectionBatchTool
Version: 0.1.6
Summary: batch import and export of Specify data
Home-page: https://github.com/jmenglund/CollectionBatchTool
Author: Markus Englund
Author-email: jan.markus.englund@gmail.com
License: MIT
Keywords: Specify,Collection management
Platform: UNKNOWN
Classifier: Development Status :: 5 - Production/Stable
Classifier: Intended Audience :: Developers
Classifier: Intended Audience :: System Administrators
Classifier: License :: OSI Approved :: MIT License
Classifier: Operating System :: OS Independent
Classifier: Programming Language :: Python
Classifier: Programming Language :: Python :: 3
Requires-Dist: pandas (>=0.16)
Requires-Dist: peewee (>=2.6)
Requires-Dist: pymysql
